{
  "matchId": "17588325",
  "homeTeam": "Jordan",
  "awayTeam": "Argentina",
  "homeScore": 1,
  "awayScore": 3,
  "phase": "F",
  "winner": "away",
  "keyEvents": [
    {
      "type": "goal",
      "team": "away",
      "minute": 7,
      "timestamp": 1782612405974
    },
    {
      "type": "var_end",
      "team": null,
      "minute": 7,
      "timestamp": 1782612431041
    },
    {
      "type": "yellow_card",
      "team": "home",
      "minute": 17,
      "timestamp": 1782613048104
    },
    {
      "type": "goal",
      "team": "away",
      "minute": 19,
      "timestamp": 1782613136218
    },
    {
      "type": "var_end",
      "team": null,
      "minute": 30,
      "timestamp": 1782613816624
    },
    {
      "type": "penalty",
      "team": "away",
      "minute": 30,
      "timestamp": 1782613821818
    },
    {
      "type": "penalty",
      "team": "away",
      "minute": 30,
      "timestamp": 1782613828843
    },
    {
      "type": "goal",
      "team": "away",
      "minute": 31,
      "timestamp": 1782613852595
    },
    {
      "type": "goal",
      "team": "away",
      "minute": 48,
      "timestamp": 1782616184361
    },
    {
      "type": "var_end",
      "team": null,
      "minute": 49,
      "timestamp": 1782616210506
    },
    {
      "type": "goal",
      "team": "home",
      "minute": 55,
      "timestamp": 1782616582869
    },
    {
      "type": "yellow_card",
      "team": "home",
      "minute": 64,
      "timestamp": 1782617129590
    },
    {
      "type": "goal",
      "team": "away",
      "minute": 80,
      "timestamp": 1782618081551
    }
  ],
  "fires": [],
  "probSeries": [
    {
      "t": 1782608404314,
      "h": 0.0455,
      "a": 0.8547
    },
    {
      "t": 1782608554492,
      "h": 0.0453,
      "a": 0.8547
    },
    {
      "t": 1782608630224,
      "h": 0.0451,
      "a": 0.8547
    },
    {
      "t": 1782608678696,
      "h": 0.0448,
      "a": 0.8547
    },
    {
      "t": 1782608769689,
      "h": 0.0451,
      "a": 0.854
    },
    {
      "t": 1782608889694,
      "h": 0.0453,
      "a": 0.854
    },
    {
      "t": 1782608924695,
      "h": 0.0451,
      "a": 0.854
    },
    {
      "t": 1782609029700,
      "h": 0.0453,
      "a": 0.854
    },
    {
      "t": 1782609134700,
      "h": 0.0451,
      "a": 0.854
    },
    {
      "t": 1782609254705,
      "h": 0.0448,
      "a": 0.8547
    },
    {
      "t": 1782609484804,
      "h": 0.0451,
      "a": 0.854
    },
    {
      "t": 1782609998296,
      "h": 0.0448,
      "a": 0.854
    },
    {
      "t": 1782610149837,
      "h": 0.0446,
      "a": 0.8547
    },
    {
      "t": 1782610186502,
      "h": 0.0455,
      "a": 0.8547
    },
    {
      "t": 1782610220468,
      "h": 0.0457,
      "a": 0.854
    },
    {
      "t": 1782610375515,
      "h": 0.0457,
      "a": 0.8547
    },
    {
      "t": 1782610515480,
      "h": 0.0461,
      "a": 0.854
    },
    {
      "t": 1782610555499,
      "h": 0.0461,
      "a": 0.854
    },
    {
      "t": 1782610595486,
      "h": 0.0461,
      "a": 0.854
    },
    {
      "t": 1782610627576,
      "h": 0.0461,
      "a": 0.8532
    },
    {
      "t": 1782610672515,
      "h": 0.0461,
      "a": 0.8532
    },
    {
      "t": 1782610735542,
      "h": 0.0461,
      "a": 0.854
    },
    {
      "t": 1782610803231,
      "h": 0.0439,
      "a": 0.8562
    },
    {
      "t": 1782610840501,
      "h": 0.0439,
      "a": 0.8562
    },
    {
      "t": 1782611009622,
      "h": 0.0443,
      "a": 0.8569
    },
    {
      "t": 1782611039722,
      "h": 0.0451,
      "a": 0.8554
    },
    {
      "t": 1782611086591,
      "h": 0.0453,
      "a": 0.8554
    },
    {
      "t": 1782611117655,
      "h": 0.0453,
      "a": 0.8554
    },
    {
      "t": 1782611197103,
      "h": 0.0457,
      "a": 0.8547
    },
    {
      "t": 1782611248769,
      "h": 0.0455,
      "a": 0.8547
    },
    {
      "t": 1782611281637,
      "h": 0.0446,
      "a": 0.8569
    },
    {
      "t": 1782611351640,
      "h": 0.0448,
      "a": 0.8562
    },
    {
      "t": 1782611412650,
      "h": 0.0446,
      "a": 0.8554
    },
    {
      "t": 1782611451704,
      "h": 0.0443,
      "a": 0.8576
    },
    {
      "t": 1782611491645,
      "h": 0.0437,
      "a": 0.8576
    },
    {
      "t": 1782611531647,
      "h": 0.0437,
      "a": 0.8569
    },
    {
      "t": 1782611572398,
      "h": 0.0437,
      "a": 0.8576
    },
    {
      "t": 1782611651653,
      "h": 0.0441,
      "a": 0.8569
    },
    {
      "t": 1782611687432,
      "h": 0.0433,
      "a": 0.8591
    },
    {
      "t": 1782611721702,
      "h": 0.0441,
      "a": 0.8554
    },
    {
      "t": 1782611788754,
      "h": 0.0429,
      "a": 0.8562
    },
    {
      "t": 1782611909608,
      "h": 0.0427,
      "a": 0.8562
    },
    {
      "t": 1782611944486,
      "h": 0.0427,
      "a": 0.8569
    },
    {
      "t": 1782611986764,
      "h": 0.0418,
      "a": 0.8584
    },
    {
      "t": 1782612020920,
      "h": 0.0403,
      "a": 0.854
    },
    {
      "t": 1782612061022,
      "h": 0.0405,
      "a": 0.8525
    },
    {
      "t": 1782612091029,
      "h": 0.0386,
      "a": 0.8584
    },
    {
      "t": 1782612126461,
      "h": 0.0392,
      "a": 0.8554
    },
    {
      "t": 1782612162312,
      "h": 0.0408,
      "a": 0.8446
    },
    {
      "t": 1782612192375,
      "h": 0.0427,
      "a": 0.8418
    },
    {
      "t": 1782612223040,
      "h": 0.0426,
      "a": 0.8432
    },
    {
      "t": 1782612253043,
      "h": 0.0435,
      "a": 0.8396
    },
    {
      "t": 1782612283838,
      "h": 0.0422,
      "a": 0.8403
    },
    {
      "t": 1782612313901,
      "h": 0.0427,
      "a": 0.8389
    },
    {
      "t": 1782612345861,
      "h": 0.0435,
      "a": 0.834
    },
    {
      "t": 1782612353041,
      "h": 0.0439,
      "a": 0.8326
    },
    {
      "t": 1782612358865,
      "h": 0.0437,
      "a": 0.8333
    },
    {
      "t": 1782612365043,
      "h": 0.0431,
      "a": 0.8347
    },
    {
      "t": 1782612370111,
      "h": 0.0427,
      "a": 0.834
    },
    {
      "t": 1782612377624,
      "h": 0.0431,
      "a": 0.8333
    },
    {
      "t": 1782612383040,
      "h": 0.0427,
      "a": 0.8347
    },
    {
      "t": 1782612389872,
      "h": 0.0427,
      "a": 0.8347
    },
    {
      "t": 1782612397097,
      "h": 0.0435,
      "a": 0.8333
    },
    {
      "t": 1782612452917,
      "h": 0.0408,
      "a": 0.8368
    },
    {
      "t": 1782612458915,
      "h": 0.042,
      "a": 0.8354
    },
    {
      "t": 1782612473920,
      "h": 0.0426,
      "a": 0.8333
    },
    {
      "t": 1782612482693,
      "h": 0.0426,
      "a": 0.8333
    },
    {
      "t": 1782612488918,
      "h": 0.0426,
      "a": 0.8333
    },
    {
      "t": 1782612496921,
      "h": 0.0426,
      "a": 0.834
    },
    {
      "t": 1782612515053,
      "h": 0.0437,
      "a": 0.8306
    },
    {
      "t": 1782612520923,
      "h": 0.0405,
      "a": 0.8333
    },
    {
      "t": 1782612528829,
      "h": 0.0386,
      "a": 0.8333
    },
    {
      "t": 1782612536932,
      "h": 0.0383,
      "a": 0.8333
    },
    {
      "t": 1782612544971,
      "h": 0.0394,
      "a": 0.8347
    },
    {
      "t": 1782612561063,
      "h": 0.0413,
      "a": 0.8354
    },
    {
      "t": 1782612572076,
      "h": 0.0412,
      "a": 0.8354
    },
    {
      "t": 1782612578939,
      "h": 0.0408,
      "a": 0.8313
    },
    {
      "t": 1782612585066,
      "h": 0.0412,
      "a": 0.8313
    },
    {
      "t": 1782612593946,
      "h": 0.042,
      "a": 0.8271
    },
    {
      "t": 1782612598968,
      "h": 0.0418,
      "a": 0.8271
    },
    {
      "t": 1782612603987,
      "h": 0.0417,
      "a": 0.8285
    },
    {
      "t": 1782612610137,
      "h": 0.0417,
      "a": 0.8285
    },
    {
      "t": 1782612617760,
      "h": 0.0412,
      "a": 0.8292
    },
    {
      "t": 1782612623710,
      "h": 0.0426,
      "a": 0.8251
    },
    {
      "t": 1782612632959,
      "h": 0.042,
      "a": 0.8258
    },
    {
      "t": 1782612641147,
      "h": 0.0435,
      "a": 0.8258
    },
    {
      "t": 1782612647069,
      "h": 0.0443,
      "a": 0.8251
    },
    {
      "t": 1782612658351,
      "h": 0.0441,
      "a": 0.8231
    },
    {
      "t": 1782612665350,
      "h": 0.0439,
      "a": 0.8224
    },
    {
      "t": 1782612674256,
      "h": 0.0451,
      "a": 0.8231
    },
    {
      "t": 1782612683073,
      "h": 0.0429,
      "a": 0.8264
    },
    {
      "t": 1782612689367,
      "h": 0.0444,
      "a": 0.8231
    },
    {
      "t": 1782612701069,
      "h": 0.0448,
      "a": 0.8231
    },
    {
      "t": 1782612731070,
      "h": 0.0424,
      "a": 0.8251
    },
    {
      "t": 1782612763004,
      "h": 0.0433,
      "a": 0.8264
    },
    {
      "t": 1782612793722,
      "h": 0.0437,
      "a": 0.8237
    },
    {
      "t": 1782612823830,
      "h": 0.0441,
      "a": 0.8244
    },
    {
      "t": 1782612854209,
      "h": 0.0455,
      "a": 0.8203
    },
    {
      "t": 1782612887493,
      "h": 0.0444,
      "a": 0.8237
    },
    {
      "t": 1782612918503,
      "h": 0.0433,
      "a": 0.8244
    },
    {
      "t": 1782612952532,
      "h": 0.0427,
      "a": 0.8264
    },
    {
      "t": 1782612988088,
      "h": 0.0453,
      "a": 0.8217
    },
    {
      "t": 1782613021095,
      "h": 0.0446,
      "a": 0.8217
    },
    {
      "t": 1782613097263,
      "h": 0.0392,
      "a": 0.8251
    },
    {
      "t": 1782613102266,
      "h": 0.0392,
      "a": 0.8251
    },
    {
      "t": 1782613107267,
      "h": 0.0391,
      "a": 0.8264
    },
    {
      "t": 1782613114637,
      "h": 0.0382,
      "a": 0.8292
    },
    {
      "t": 1782613120131,
      "h": 0.0377,
      "a": 0.8299
    },
    {
      "t": 1782613129644,
      "h": 0.0372,
      "a": 0.8313
    },
    {
      "t": 1782613192875,
      "h": 0.0071,
      "a": 0.9515
    },
    {
      "t": 1782613205891,
      "h": 0.0071,
      "a": 0.9515
    },
    {
      "t": 1782613211172,
      "h": 0.0127,
      "a": 0.9355
    },
    {
      "t": 1782613227983,
      "h": 0.0091,
      "a": 0.9425
    },
    {
      "t": 1782613240076,
      "h": 0.0091,
      "a": 0.9425
    },
    {
      "t": 1782613260304,
      "h": 0.0118,
      "a": 0.9407
    },
    {
      "t": 1782613273083,
      "h": 0.0119,
      "a": 0.9416
    },
    {
      "t": 1782613280880,
      "h": 0.0106,
      "a": 0.9461
    },
    {
      "t": 1782613291316,
      "h": 0.0116,
      "a": 0.9416
    },
    {
      "t": 1782613301315,
      "h": 0.0109,
      "a": 0.9416
    },
    {
      "t": 1782613310565,
      "h": 0.0121,
      "a": 0.9363
    },
    {
      "t": 1782613316316,
      "h": 0.0115,
      "a": 0.9363
    },
    {
      "t": 1782613323183,
      "h": 0.011,
      "a": 0.9372
    },
    {
      "t": 1782613338506,
      "h": 0.0115,
      "a": 0.9372
    },
    {
      "t": 1782613353432,
      "h": 0.0116,
      "a": 0.9363
    },
    {
      "t": 1782613359192,
      "h": 0.0127,
      "a": 0.9337
    },
    {
      "t": 1782613367346,
      "h": 0.0128,
      "a": 0.9372
    },
    {
      "t": 1782613382198,
      "h": 0.0122,
      "a": 0.9355
    },
    {
      "t": 1782613393325,
      "h": 0.0124,
      "a": 0.9355
    },
    {
      "t": 1782613403200,
      "h": 0.0128,
      "a": 0.9337
    },
    {
      "t": 1782613410202,
      "h": 0.0127,
      "a": 0.9337
    },
    {
      "t": 1782613428330,
      "h": 0.0121,
      "a": 0.9337
    },
    {
      "t": 1782613435209,
      "h": 0.0127,
      "a": 0.9355
    },
    {
      "t": 1782613486291,
      "h": 0.0104,
      "a": 0.939
    },
    {
      "t": 1782613518336,
      "h": 0.0121,
      "a": 0.9355
    },
    {
      "t": 1782613548500,
      "h": 0.0116,
      "a": 0.9372
    },
    {
      "t": 1782613583499,
      "h": 0.0091,
      "a": 0.9407
    },
    {
      "t": 1782613614269,
      "h": 0.01,
      "a": 0.9416
    },
    {
      "t": 1782613644709,
      "h": 0.01,
      "a": 0.9425
    },
    {
      "t": 1782613674906,
      "h": 0.0091,
      "a": 0.9425
    },
    {
      "t": 1782613740712,
      "h": 0.0122,
      "a": 0.9399
    },
    {
      "t": 1782613822920,
      "h": 0.0128,
      "a": 0.9363
    },
    {
      "t": 1782614853911,
      "h": 0.0039,
      "a": 0.9843
    },
    {
      "t": 1782615118963,
      "h": 0.0039,
      "a": 0.9823
    },
    {
      "t": 1782616589607,
      "h": 0.0077,
      "a": 0.9434
    },
    {
      "t": 1782616595983,
      "h": 0.0056,
      "a": 0.9551
    },
    {
      "t": 1782616614487,
      "h": 0.0056,
      "a": 0.9606
    },
    {
      "t": 1782616620284,
      "h": 0.0059,
      "a": 0.9588
    },
    {
      "t": 1782616629482,
      "h": 0.0059,
      "a": 0.9588
    },
    {
      "t": 1782616639491,
      "h": 0.0059,
      "a": 0.9588
    },
    {
      "t": 1782616644491,
      "h": 0.0067,
      "a": 0.9542
    },
    {
      "t": 1782616649706,
      "h": 0.0067,
      "a": 0.9524
    },
    {
      "t": 1782616667485,
      "h": 0.0063,
      "a": 0.9551
    },
    {
      "t": 1782616673535,
      "h": 0.0063,
      "a": 0.9569
    },
    {
      "t": 1782616683483,
      "h": 0.0071,
      "a": 0.9533
    },
    {
      "t": 1782616690495,
      "h": 0.0067,
      "a": 0.9533
    },
    {
      "t": 1782616699270,
      "h": 0.0063,
      "a": 0.9551
    },
    {
      "t": 1782616738274,
      "h": 0.0067,
      "a": 0.9533
    },
    {
      "t": 1782616745514,
      "h": 0.0063,
      "a": 0.9542
    },
    {
      "t": 1782616750528,
      "h": 0.0063,
      "a": 0.9515
    },
    {
      "t": 1782616758189,
      "h": 0.0063,
      "a": 0.9533
    },
    {
      "t": 1782616769566,
      "h": 0.0067,
      "a": 0.9533
    },
    {
      "t": 1782616779676,
      "h": 0.0067,
      "a": 0.9542
    },
    {
      "t": 1782616788186,
      "h": 0.0067,
      "a": 0.9551
    },
    {
      "t": 1782616799511,
      "h": 0.0063,
      "a": 0.9588
    },
    {
      "t": 1782616811534,
      "h": 0.0071,
      "a": 0.9542
    },
    {
      "t": 1782616838132,
      "h": 0.0077,
      "a": 0.9425
    },
    {
      "t": 1782616843310,
      "h": 0.0071,
      "a": 0.9524
    },
    {
      "t": 1782616861494,
      "h": 0.0071,
      "a": 0.9588
    },
    {
      "t": 1782616872546,
      "h": 0.0067,
      "a": 0.956
    },
    {
      "t": 1782616879495,
      "h": 0.0063,
      "a": 0.9588
    },
    {
      "t": 1782616912555,
      "h": 0.0067,
      "a": 0.9569
    },
    {
      "t": 1782617125219,
      "h": 0.0032,
      "a": 0.9662
    },
    {
      "t": 1782617370429,
      "h": 0.0033,
      "a": 0.9671
    },
    {
      "t": 1782617400509,
      "h": 0.0029,
      "a": 0.9737
    },
    {
      "t": 1782617470603,
      "h": 0.0031,
      "a": 0.9662
    },
    {
      "t": 1782617530378,
      "h": 0.0053,
      "a": 0.9634
    },
    {
      "t": 1782617563778,
      "h": 0.0037,
      "a": 0.969
    },
    {
      "t": 1782617599860,
      "h": 0.0037,
      "a": 0.969
    },
    {
      "t": 1782617632018,
      "h": 0.0027,
      "a": 0.9709
    },
    {
      "t": 1782617662173,
      "h": 0.0039,
      "a": 0.9643
    },
    {
      "t": 1782617692354,
      "h": 0.004,
      "a": 0.9634
    },
    {
      "t": 1782617727574,
      "h": 0.0037,
      "a": 0.9662
    },
    {
      "t": 1782617759577,
      "h": 0.0044,
      "a": 0.9653
    },
    {
      "t": 1782617793581,
      "h": 0.0037,
      "a": 0.9625
    },
    {
      "t": 1782617823582,
      "h": 0.0046,
      "a": 0.9606
    },
    {
      "t": 1782617857293,
      "h": 0.0036,
      "a": 0.9643
    },
    {
      "t": 1782617893833,
      "h": 0.0036,
      "a": 0.9551
    },
    {
      "t": 1782617936235,
      "h": 0.0032,
      "a": 0.9542
    },
    {
      "t": 1782617970929,
      "h": 0.0036,
      "a": 0.956
    },
    {
      "t": 1782618056143,
      "h": 0.0053,
      "a": 0.9533
    },
    {
      "t": 1782618064273,
      "h": 0.0056,
      "a": 0.9533
    },
    {
      "t": 1782618076694,
      "h": 0.0053,
      "a": 0.9506
    }
  ],
  "computedAt": "2026-07-15T07:26:51.487Z"
}