{
  "matchId": "18175983",
  "homeTeam": "Germany",
  "awayTeam": "Paraguay",
  "homeScore": 1,
  "awayScore": 1,
  "phase": "FPE",
  "winner": "draw",
  "keyEvents": [
    {
      "type": "goal",
      "team": "away",
      "minute": 42,
      "timestamp": 1782767497964
    },
    {
      "type": "goal",
      "team": "home",
      "minute": 54,
      "timestamp": 1782769614619
    },
    {
      "type": "yellow_card",
      "team": "away",
      "minute": 65,
      "timestamp": 1782770247170
    },
    {
      "type": "var_end",
      "team": null,
      "minute": 99,
      "timestamp": 1782772893076
    },
    {
      "type": "goal",
      "team": "home",
      "minute": 102,
      "timestamp": 1782773105397
    },
    {
      "type": "var_end",
      "team": null,
      "minute": 105,
      "timestamp": 1782773293611
    },
    {
      "type": "yellow_card",
      "team": "home",
      "minute": 106,
      "timestamp": 1782773762393
    },
    {
      "type": "yellow_card",
      "team": "home",
      "minute": 115,
      "timestamp": 1782774311648
    },
    {
      "type": "yellow_card",
      "team": "away",
      "minute": 117,
      "timestamp": 1782774432721
    }
  ],
  "fires": [
    {
      "signalRegistryId": "719d89c2-c1fc-4061-8c81-ba099322848f",
      "strategy": "A",
      "matchId": "18175983",
      "homeTeam": "Germany",
      "awayTeam": "Paraguay",
      "triggerEvent": "goal",
      "triggerMinute": 54,
      "preEventHomeProb": 0.32185,
      "preEventAwayProb": 0.07299,
      "postSignalHomeProb": 0.60827,
      "postSignalAwayProb": 0.07299,
      "delta": 0.28641999999999995,
      "windowSeconds": 61.435,
      "favouredTeam": "home",
      "position": "long_home",
      "recoveredFromSnapshot": false,
      "onchainStatus": "pending",
      "subscribersNotified": 0,
      "subscribersFailed": 0,
      "firedAt": 1782769676054,
      "outcome": "miss",
      "actualWinner": "draw"
    },
    {
      "signalRegistryId": "719d89c2-c1fc-4061-8c81-ba099322848f",
      "strategy": "B",
      "matchId": "18175983",
      "homeTeam": "Germany",
      "awayTeam": "Paraguay",
      "triggerEvent": "goal",
      "triggerMinute": 54,
      "preEventHomeProb": 0.32185,
      "preEventAwayProb": 0.07299,
      "postSignalHomeProb": 0.60827,
      "postSignalAwayProb": 0.07299,
      "delta": 0.28641999999999995,
      "windowSeconds": 61.435,
      "favouredTeam": "home",
      "position": "short_home",
      "recoveredFromSnapshot": false,
      "onchainStatus": "pending",
      "subscribersNotified": 0,
      "subscribersFailed": 0,
      "firedAt": 1782769676054,
      "outcome": "hit",
      "actualWinner": "draw"
    }
  ],
  "probSeries": [
    {
      "t": 1782761460437,
      "h": 0.7353,
      "a": 0.0893
    },
    {
      "t": 1782761492543,
      "h": 0.7358,
      "a": 0.0893
    },
    {
      "t": 1782761533964,
      "h": 0.7369,
      "a": 0.0885
    },
    {
      "t": 1782761579391,
      "h": 0.7364,
      "a": 0.0885
    },
    {
      "t": 1782761651557,
      "h": 0.7353,
      "a": 0.0893
    },
    {
      "t": 1782761681567,
      "h": 0.7342,
      "a": 0.0893
    },
    {
      "t": 1782761714565,
      "h": 0.7358,
      "a": 0.0885
    },
    {
      "t": 1782761748969,
      "h": 0.7337,
      "a": 0.0901
    },
    {
      "t": 1782761786577,
      "h": 0.7326,
      "a": 0.0909
    },
    {
      "t": 1782761819575,
      "h": 0.731,
      "a": 0.0909
    },
    {
      "t": 1782761858973,
      "h": 0.7305,
      "a": 0.0917
    },
    {
      "t": 1782761939781,
      "h": 0.7278,
      "a": 0.0926
    },
    {
      "t": 1782761979711,
      "h": 0.7278,
      "a": 0.0926
    },
    {
      "t": 1782762041590,
      "h": 0.7257,
      "a": 0.0943
    },
    {
      "t": 1782762220370,
      "h": 0.7236,
      "a": 0.0962
    },
    {
      "t": 1782762251609,
      "h": 0.7236,
      "a": 0.0952
    },
    {
      "t": 1782762311608,
      "h": 0.7231,
      "a": 0.0962
    },
    {
      "t": 1782762348997,
      "h": 0.7236,
      "a": 0.0962
    },
    {
      "t": 1782762380614,
      "h": 0.7267,
      "a": 0.0943
    },
    {
      "t": 1782762414154,
      "h": 0.7273,
      "a": 0.0943
    },
    {
      "t": 1782762450771,
      "h": 0.7273,
      "a": 0.0943
    },
    {
      "t": 1782762481915,
      "h": 0.7273,
      "a": 0.0943
    },
    {
      "t": 1782762530629,
      "h": 0.7273,
      "a": 0.0943
    },
    {
      "t": 1782762608637,
      "h": 0.7273,
      "a": 0.0943
    },
    {
      "t": 1782762649860,
      "h": 0.7289,
      "a": 0.0926
    },
    {
      "t": 1782762723816,
      "h": 0.7289,
      "a": 0.0935
    },
    {
      "t": 1782762758653,
      "h": 0.7289,
      "a": 0.0926
    },
    {
      "t": 1782762834540,
      "h": 0.7289,
      "a": 0.0926
    },
    {
      "t": 1782762869017,
      "h": 0.7294,
      "a": 0.0926
    },
    {
      "t": 1782762919825,
      "h": 0.7289,
      "a": 0.0926
    },
    {
      "t": 1782762949886,
      "h": 0.7283,
      "a": 0.0926
    },
    {
      "t": 1782762983675,
      "h": 0.7283,
      "a": 0.0926
    },
    {
      "t": 1782763037690,
      "h": 0.7283,
      "a": 0.0926
    },
    {
      "t": 1782763136682,
      "h": 0.7283,
      "a": 0.0926
    },
    {
      "t": 1782763189028,
      "h": 0.7278,
      "a": 0.0935
    },
    {
      "t": 1782763232700,
      "h": 0.7278,
      "a": 0.0935
    },
    {
      "t": 1782763292755,
      "h": 0.7278,
      "a": 0.0935
    },
    {
      "t": 1782763379035,
      "h": 0.7283,
      "a": 0.0926
    },
    {
      "t": 1782763413698,
      "h": 0.7299,
      "a": 0.0909
    },
    {
      "t": 1782763448718,
      "h": 0.7299,
      "a": 0.0909
    },
    {
      "t": 1782763505748,
      "h": 0.7299,
      "a": 0.0909
    },
    {
      "t": 1782763537194,
      "h": 0.7299,
      "a": 0.0901
    },
    {
      "t": 1782763570060,
      "h": 0.7299,
      "a": 0.0909
    },
    {
      "t": 1782763622912,
      "h": 0.7299,
      "a": 0.0909
    },
    {
      "t": 1782763679363,
      "h": 0.7278,
      "a": 0.0917
    },
    {
      "t": 1782763719046,
      "h": 0.7273,
      "a": 0.0917
    },
    {
      "t": 1782763769177,
      "h": 0.7283,
      "a": 0.0917
    },
    {
      "t": 1782763822135,
      "h": 0.7305,
      "a": 0.0909
    },
    {
      "t": 1782763929050,
      "h": 0.731,
      "a": 0.0909
    },
    {
      "t": 1782764024053,
      "h": 0.731,
      "a": 0.0909
    },
    {
      "t": 1782764144060,
      "h": 0.7315,
      "a": 0.0901
    },
    {
      "t": 1782764216826,
      "h": 0.7315,
      "a": 0.0901
    },
    {
      "t": 1782764294829,
      "h": 0.731,
      "a": 0.0901
    },
    {
      "t": 1782764336667,
      "h": 0.7294,
      "a": 0.0909
    },
    {
      "t": 1782764367759,
      "h": 0.7289,
      "a": 0.0917
    },
    {
      "t": 1782764469969,
      "h": 0.7289,
      "a": 0.0917
    },
    {
      "t": 1782764502944,
      "h": 0.7305,
      "a": 0.0917
    },
    {
      "t": 1782764534865,
      "h": 0.7299,
      "a": 0.0926
    },
    {
      "t": 1782764569072,
      "h": 0.7294,
      "a": 0.0926
    },
    {
      "t": 1782764604072,
      "h": 0.7283,
      "a": 0.0935
    },
    {
      "t": 1782764634072,
      "h": 0.7299,
      "a": 0.0909
    },
    {
      "t": 1782764666882,
      "h": 0.7283,
      "a": 0.0917
    },
    {
      "t": 1782764696885,
      "h": 0.7299,
      "a": 0.0909
    },
    {
      "t": 1782764727423,
      "h": 0.7305,
      "a": 0.0901
    },
    {
      "t": 1782764799076,
      "h": 0.7299,
      "a": 0.0909
    },
    {
      "t": 1782764831898,
      "h": 0.7294,
      "a": 0.0917
    },
    {
      "t": 1782764861952,
      "h": 0.7299,
      "a": 0.0909
    },
    {
      "t": 1782764894080,
      "h": 0.7342,
      "a": 0.0885
    },
    {
      "t": 1782764934081,
      "h": 0.7299,
      "a": 0.0909
    },
    {
      "t": 1782764970507,
      "h": 0.7299,
      "a": 0.0909
    },
    {
      "t": 1782765009728,
      "h": 0.7138,
      "a": 0.1034
    },
    {
      "t": 1782765047682,
      "h": 0.7179,
      "a": 0.0962
    },
    {
      "t": 1782765079729,
      "h": 0.7169,
      "a": 0.0952
    },
    {
      "t": 1782765111736,
      "h": 0.7128,
      "a": 0.098
    },
    {
      "t": 1782765141818,
      "h": 0.7148,
      "a": 0.0971
    },
    {
      "t": 1782765173541,
      "h": 0.7102,
      "a": 0.098
    },
    {
      "t": 1782765203740,
      "h": 0.7037,
      "a": 0.1018
    },
    {
      "t": 1782765242007,
      "h": 0.7042,
      "a": 0.1011
    },
    {
      "t": 1782765273742,
      "h": 0.6998,
      "a": 0.1031
    },
    {
      "t": 1782765308749,
      "h": 0.7008,
      "a": 0.1015
    },
    {
      "t": 1782765346255,
      "h": 0.7018,
      "a": 0.1012
    },
    {
      "t": 1782765382766,
      "h": 0.7013,
      "a": 0.099
    },
    {
      "t": 1782765414204,
      "h": 0.7018,
      "a": 0.1004
    },
    {
      "t": 1782765444787,
      "h": 0.7087,
      "a": 0.0962
    },
    {
      "t": 1782765475766,
      "h": 0.7047,
      "a": 0.098
    },
    {
      "t": 1782765506802,
      "h": 0.7022,
      "a": 0.099
    },
    {
      "t": 1782765538811,
      "h": 0.7027,
      "a": 0.099
    },
    {
      "t": 1782765568818,
      "h": 0.7022,
      "a": 0.1
    },
    {
      "t": 1782765598940,
      "h": 0.7027,
      "a": 0.098
    },
    {
      "t": 1782765630065,
      "h": 0.7003,
      "a": 0.099
    },
    {
      "t": 1782765661777,
      "h": 0.7052,
      "a": 0.0971
    },
    {
      "t": 1782765691852,
      "h": 0.7077,
      "a": 0.0935
    },
    {
      "t": 1782765722871,
      "h": 0.7087,
      "a": 0.0926
    },
    {
      "t": 1782765757785,
      "h": 0.7072,
      "a": 0.0935
    },
    {
      "t": 1782765790176,
      "h": 0.7102,
      "a": 0.0909
    },
    {
      "t": 1782765820596,
      "h": 0.7122,
      "a": 0.0901
    },
    {
      "t": 1782765855185,
      "h": 0.7117,
      "a": 0.0909
    },
    {
      "t": 1782765885203,
      "h": 0.7122,
      "a": 0.0909
    },
    {
      "t": 1782765916208,
      "h": 0.7107,
      "a": 0.0917
    },
    {
      "t": 1782765946873,
      "h": 0.7102,
      "a": 0.0917
    },
    {
      "t": 1782765980150,
      "h": 0.7128,
      "a": 0.0885
    },
    {
      "t": 1782766010164,
      "h": 0.7117,
      "a": 0.0893
    },
    {
      "t": 1782766040954,
      "h": 0.7107,
      "a": 0.0901
    },
    {
      "t": 1782766071826,
      "h": 0.7062,
      "a": 0.0917
    },
    {
      "t": 1782766101940,
      "h": 0.7052,
      "a": 0.0926
    },
    {
      "t": 1782766134226,
      "h": 0.7082,
      "a": 0.0909
    },
    {
      "t": 1782766164982,
      "h": 0.7072,
      "a": 0.0901
    },
    {
      "t": 1782766195822,
      "h": 0.7072,
      "a": 0.0901
    },
    {
      "t": 1782766231290,
      "h": 0.7042,
      "a": 0.0901
    },
    {
      "t": 1782766261834,
      "h": 0.7107,
      "a": 0.0893
    },
    {
      "t": 1782766292612,
      "h": 0.7102,
      "a": 0.0885
    },
    {
      "t": 1782766322711,
      "h": 0.7082,
      "a": 0.087
    },
    {
      "t": 1782766355355,
      "h": 0.7097,
      "a": 0.0847
    },
    {
      "t": 1782766385376,
      "h": 0.7067,
      "a": 0.0877
    },
    {
      "t": 1782766423397,
      "h": 0.7032,
      "a": 0.0885
    },
    {
      "t": 1782766453846,
      "h": 0.7018,
      "a": 0.0885
    },
    {
      "t": 1782766487341,
      "h": 0.7008,
      "a": 0.0877
    },
    {
      "t": 1782766518459,
      "h": 0.7037,
      "a": 0.0855
    },
    {
      "t": 1782766556768,
      "h": 0.7018,
      "a": 0.087
    },
    {
      "t": 1782766587090,
      "h": 0.7042,
      "a": 0.0847
    },
    {
      "t": 1782766618106,
      "h": 0.6993,
      "a": 0.0862
    },
    {
      "t": 1782766649054,
      "h": 0.6988,
      "a": 0.0847
    },
    {
      "t": 1782766679551,
      "h": 0.7037,
      "a": 0.0813
    },
    {
      "t": 1782766710188,
      "h": 0.7032,
      "a": 0.0826
    },
    {
      "t": 1782766742327,
      "h": 0.7018,
      "a": 0.0826
    },
    {
      "t": 1782766776112,
      "h": 0.7022,
      "a": 0.082
    },
    {
      "t": 1782766810207,
      "h": 0.7003,
      "a": 0.0833
    },
    {
      "t": 1782766844758,
      "h": 0.694,
      "a": 0.0855
    },
    {
      "t": 1782766875263,
      "h": 0.6859,
      "a": 0.0885
    },
    {
      "t": 1782766906438,
      "h": 0.6845,
      "a": 0.0877
    },
    {
      "t": 1782766937443,
      "h": 0.6817,
      "a": 0.0877
    },
    {
      "t": 1782766971258,
      "h": 0.6789,
      "a": 0.0877
    },
    {
      "t": 1782767001974,
      "h": 0.6761,
      "a": 0.0877
    },
    {
      "t": 1782767032836,
      "h": 0.677,
      "a": 0.0901
    },
    {
      "t": 1782767064335,
      "h": 0.6752,
      "a": 0.0901
    },
    {
      "t": 1782767095316,
      "h": 0.6725,
      "a": 0.0917
    },
    {
      "t": 1782767126339,
      "h": 0.6739,
      "a": 0.0909
    },
    {
      "t": 1782767157196,
      "h": 0.6711,
      "a": 0.0909
    },
    {
      "t": 1782767188849,
      "h": 0.6702,
      "a": 0.0909
    },
    {
      "t": 1782767220379,
      "h": 0.6716,
      "a": 0.0877
    },
    {
      "t": 1782767258774,
      "h": 0.6702,
      "a": 0.0877
    },
    {
      "t": 1782767294860,
      "h": 0.6716,
      "a": 0.087
    },
    {
      "t": 1782767325461,
      "h": 0.6631,
      "a": 0.087
    },
    {
      "t": 1782767356423,
      "h": 0.6614,
      "a": 0.084
    },
    {
      "t": 1782767387560,
      "h": 0.6627,
      "a": 0.0826
    },
    {
      "t": 1782767417580,
      "h": 0.6601,
      "a": 0.0826
    },
    {
      "t": 1782767438438,
      "h": 0.6592,
      "a": 0.0826
    },
    {
      "t": 1782767445456,
      "h": 0.6583,
      "a": 0.0833
    },
    {
      "t": 1782767450537,
      "h": 0.657,
      "a": 0.0833
    },
    {
      "t": 1782767461456,
      "h": 0.6557,
      "a": 0.0847
    },
    {
      "t": 1782767466543,
      "h": 0.6545,
      "a": 0.0855
    },
    {
      "t": 1782767474875,
      "h": 0.6506,
      "a": 0.0862
    },
    {
      "t": 1782767480449,
      "h": 0.6498,
      "a": 0.087
    },
    {
      "t": 1782767487013,
      "h": 0.6481,
      "a": 0.0877
    },
    {
      "t": 1782767492343,
      "h": 0.6481,
      "a": 0.0877
    },
    {
      "t": 1782767553493,
      "h": 0.3671,
      "a": 0.3129
    },
    {
      "t": 1782767560495,
      "h": 0.3687,
      "a": 0.3107
    },
    {
      "t": 1782767566494,
      "h": 0.3689,
      "a": 0.3106
    },
    {
      "t": 1782767574112,
      "h": 0.3995,
      "a": 0.2834
    },
    {
      "t": 1782767579618,
      "h": 0.4005,
      "a": 0.2823
    },
    {
      "t": 1782767586606,
      "h": 0.3986,
      "a": 0.2807
    },
    {
      "t": 1782767591919,
      "h": 0.3953,
      "a": 0.2828
    },
    {
      "t": 1782767600498,
      "h": 0.3953,
      "a": 0.283
    },
    {
      "t": 1782767606513,
      "h": 0.3949,
      "a": 0.2833
    },
    {
      "t": 1782767611695,
      "h": 0.3997,
      "a": 0.281
    },
    {
      "t": 1782767618159,
      "h": 0.3995,
      "a": 0.28
    },
    {
      "t": 1782767624501,
      "h": 0.4034,
      "a": 0.2772
    },
    {
      "t": 1782767630504,
      "h": 0.4002,
      "a": 0.2802
    },
    {
      "t": 1782767636504,
      "h": 0.4029,
      "a": 0.28
    },
    {
      "t": 1782767641572,
      "h": 0.407,
      "a": 0.2766
    },
    {
      "t": 1782767647995,
      "h": 0.4054,
      "a": 0.2777
    },
    {
      "t": 1782767653179,
      "h": 0.405,
      "a": 0.2778
    },
    {
      "t": 1782767658544,
      "h": 0.4058,
      "a": 0.2754
    },
    {
      "t": 1782767666147,
      "h": 0.4052,
      "a": 0.2761
    },
    {
      "t": 1782767671516,
      "h": 0.4063,
      "a": 0.2744
    },
    {
      "t": 1782767677654,
      "h": 0.4054,
      "a": 0.2749
    },
    {
      "t": 1782767682892,
      "h": 0.4085,
      "a": 0.2732
    },
    {
      "t": 1782767689099,
      "h": 0.409,
      "a": 0.2745
    },
    {
      "t": 1782767696208,
      "h": 0.4075,
      "a": 0.2742
    },
    {
      "t": 1782767702257,
      "h": 0.4058,
      "a": 0.2741
    },
    {
      "t": 1782767711217,
      "h": 0.4054,
      "a": 0.2743
    },
    {
      "t": 1782767716619,
      "h": 0.4047,
      "a": 0.2762
    },
    {
      "t": 1782767722893,
      "h": 0.4047,
      "a": 0.2757
    },
    {
      "t": 1782767728894,
      "h": 0.4067,
      "a": 0.2744
    },
    {
      "t": 1782767736683,
      "h": 0.4058,
      "a": 0.2748
    },
    {
      "t": 1782767744238,
      "h": 0.406,
      "a": 0.2747
    },
    {
      "t": 1782767750245,
      "h": 0.4065,
      "a": 0.2742
    },
    {
      "t": 1782767755549,
      "h": 0.4098,
      "a": 0.2724
    },
    {
      "t": 1782767761552,
      "h": 0.411,
      "a": 0.2712
    },
    {
      "t": 1782767770394,
      "h": 0.411,
      "a": 0.2719
    },
    {
      "t": 1782767775558,
      "h": 0.4087,
      "a": 0.273
    },
    {
      "t": 1782767790559,
      "h": 0.4077,
      "a": 0.2712
    },
    {
      "t": 1782767795736,
      "h": 0.4102,
      "a": 0.2693
    },
    {
      "t": 1782767826571,
      "h": 0.4087,
      "a": 0.2734
    },
    {
      "t": 1782767856576,
      "h": 0.4067,
      "a": 0.2752
    },
    {
      "t": 1782767886586,
      "h": 0.4042,
      "a": 0.2751
    },
    {
      "t": 1782767918917,
      "h": 0.3968,
      "a": 0.2801
    },
    {
      "t": 1782767949776,
      "h": 0.3995,
      "a": 0.2772
    },
    {
      "t": 1782767985385,
      "h": 0.3965,
      "a": 0.2783
    },
    {
      "t": 1782768016927,
      "h": 0.3912,
      "a": 0.2788
    },
    {
      "t": 1782768050635,
      "h": 0.3909,
      "a": 0.2786
    },
    {
      "t": 1782768086703,
      "h": 0.3928,
      "a": 0.276
    },
    {
      "t": 1782768130653,
      "h": 0.3954,
      "a": 0.2773
    },
    {
      "t": 1782768166485,
      "h": 0.3905,
      "a": 0.2774
    },
    {
      "t": 1782768210708,
      "h": 0.392,
      "a": 0.2764
    },
    {
      "t": 1782768244934,
      "h": 0.3945,
      "a": 0.2794
    },
    {
      "t": 1782768276561,
      "h": 0.4015,
      "a": 0.2721
    },
    {
      "t": 1782768328698,
      "h": 0.3992,
      "a": 0.2752
    },
    {
      "t": 1782768361715,
      "h": 0.3971,
      "a": 0.2757
    },
    {
      "t": 1782768421748,
      "h": 0.3981,
      "a": 0.2749
    },
    {
      "t": 1782768521217,
      "h": 0.4,
      "a": 0.2688
    },
    {
      "t": 1782768564243,
      "h": 0.3978,
      "a": 0.2749
    },
    {
      "t": 1782768601779,
      "h": 0.3967,
      "a": 0.2756
    },
    {
      "t": 1782768634961,
      "h": 0.3959,
      "a": 0.2768
    },
    {
      "t": 1782768692803,
      "h": 0.3973,
      "a": 0.2797
    },
    {
      "t": 1782768780820,
      "h": 0.3957,
      "a": 0.2779
    },
    {
      "t": 1782768825834,
      "h": 0.3959,
      "a": 0.278
    },
    {
      "t": 1782768870843,
      "h": 0.3949,
      "a": 0.2787
    },
    {
      "t": 1782768901849,
      "h": 0.4002,
      "a": 0.2854
    },
    {
      "t": 1782768940854,
      "h": 0.396,
      "a": 0.2792
    },
    {
      "t": 1782768985864,
      "h": 0.3931,
      "a": 0.2806
    },
    {
      "t": 1782769016986,
      "h": 0.3928,
      "a": 0.2792
    },
    {
      "t": 1782769102995,
      "h": 0.3917,
      "a": 0.2774
    },
    {
      "t": 1782769138089,
      "h": 0.3911,
      "a": 0.2809
    },
    {
      "t": 1782769170110,
      "h": 0.3839,
      "a": 0.2834
    },
    {
      "t": 1782769200129,
      "h": 0.3831,
      "a": 0.2844
    },
    {
      "t": 1782769236152,
      "h": 0.3786,
      "a": 0.2876
    },
    {
      "t": 1782769267010,
      "h": 0.3748,
      "a": 0.2903
    },
    {
      "t": 1782769299960,
      "h": 0.3727,
      "a": 0.292
    },
    {
      "t": 1782769329974,
      "h": 0.37,
      "a": 0.2939
    },
    {
      "t": 1782769359975,
      "h": 0.3631,
      "a": 0.2985
    },
    {
      "t": 1782769389981,
      "h": 0.3605,
      "a": 0.3008
    },
    {
      "t": 1782769419988,
      "h": 0.357,
      "a": 0.3041
    },
    {
      "t": 1782769455031,
      "h": 0.3497,
      "a": 0.3101
    },
    {
      "t": 1782769485296,
      "h": 0.3452,
      "a": 0.3135
    },
    {
      "t": 1782769516011,
      "h": 0.3389,
      "a": 0.3193
    },
    {
      "t": 1782769546718,
      "h": 0.3368,
      "a": 0.3181
    },
    {
      "t": 1782769559037,
      "h": 0.3354,
      "a": 0.3196
    },
    {
      "t": 1782769564648,
      "h": 0.3323,
      "a": 0.3226
    },
    {
      "t": 1782769570025,
      "h": 0.3298,
      "a": 0.3251
    },
    {
      "t": 1782769577058,
      "h": 0.3293,
      "a": 0.3247
    },
    {
      "t": 1782769583684,
      "h": 0.3259,
      "a": 0.3278
    },
    {
      "t": 1782769589040,
      "h": 0.3258,
      "a": 0.3281
    },
    {
      "t": 1782769595032,
      "h": 0.3257,
      "a": 0.3281
    },
    {
      "t": 1782769600032,
      "h": 0.3236,
      "a": 0.3301
    },
    {
      "t": 1782769605034,
      "h": 0.3232,
      "a": 0.3303
    },
    {
      "t": 1782769610038,
      "h": 0.3223,
      "a": 0.3287
    },
    {
      "t": 1782769676054,
      "h": 0.6083,
      "a": 0.073
    },
    {
      "t": 1782769682080,
      "h": 0.5872,
      "a": 0.073
    },
    {
      "t": 1782769688053,
      "h": 0.5834,
      "a": 0.0752
    },
    {
      "t": 1782769693420,
      "h": 0.5794,
      "a": 0.0775
    },
    {
      "t": 1782769698421,
      "h": 0.5801,
      "a": 0.0813
    },
    {
      "t": 1782769705051,
      "h": 0.579,
      "a": 0.0813
    },
    {
      "t": 1782769715018,
      "h": 0.5787,
      "a": 0.0794
    },
    {
      "t": 1782769720062,
      "h": 0.5797,
      "a": 0.0763
    },
    {
      "t": 1782769725290,
      "h": 0.579,
      "a": 0.0787
    },
    {
      "t": 1782769732287,
      "h": 0.5787,
      "a": 0.0781
    },
    {
      "t": 1782769751027,
      "h": 0.578,
      "a": 0.0741
    },
    {
      "t": 1782769757234,
      "h": 0.5777,
      "a": 0.073
    },
    {
      "t": 1782769763058,
      "h": 0.5764,
      "a": 0.0735
    },
    {
      "t": 1782769768080,
      "h": 0.5744,
      "a": 0.0741
    },
    {
      "t": 1782769777498,
      "h": 0.5811,
      "a": 0.0704
    },
    {
      "t": 1782769785082,
      "h": 0.5741,
      "a": 0.0719
    },
    {
      "t": 1782769790086,
      "h": 0.5737,
      "a": 0.0714
    },
    {
      "t": 1782769795089,
      "h": 0.5737,
      "a": 0.0699
    },
    {
      "t": 1782769801060,
      "h": 0.5741,
      "a": 0.069
    },
    {
      "t": 1782769806087,
      "h": 0.5741,
      "a": 0.069
    },
    {
      "t": 1782769812032,
      "h": 0.5734,
      "a": 0.0685
    },
    {
      "t": 1782769817063,
      "h": 0.5731,
      "a": 0.0676
    },
    {
      "t": 1782769825511,
      "h": 0.5721,
      "a": 0.0685
    },
    {
      "t": 1782769831098,
      "h": 0.5679,
      "a": 0.0714
    },
    {
      "t": 1782769836099,
      "h": 0.5692,
      "a": 0.0709
    },
    {
      "t": 1782769841544,
      "h": 0.5747,
      "a": 0.069
    },
    {
      "t": 1782769849519,
      "h": 0.5757,
      "a": 0.0685
    },
    {
      "t": 1782769855523,
      "h": 0.576,
      "a": 0.0685
    },
    {
      "t": 1782769861109,
      "h": 0.5744,
      "a": 0.0685
    },
    {
      "t": 1782769866702,
      "h": 0.5774,
      "a": 0.0667
    },
    {
      "t": 1782769871914,
      "h": 0.5744,
      "a": 0.0685
    },
    {
      "t": 1782769877628,
      "h": 0.575,
      "a": 0.0658
    },
    {
      "t": 1782769883069,
      "h": 0.5757,
      "a": 0.0658
    },
    {
      "t": 1782769894125,
      "h": 0.5757,
      "a": 0.0658
    },
    {
      "t": 1782769903059,
      "h": 0.5777,
      "a": 0.0658
    },
    {
      "t": 1782769910128,
      "h": 0.5734,
      "a": 0.0654
    },
    {
      "t": 1782769941074,
      "h": 0.5741,
      "a": 0.0649
    },
    {
      "t": 1782769973078,
      "h": 0.5666,
      "a": 0.0658
    },
    {
      "t": 1782770005126,
      "h": 0.5602,
      "a": 0.0649
    },
    {
      "t": 1782770036155,
      "h": 0.5577,
      "a": 0.0667
    },
    {
      "t": 1782770067710,
      "h": 0.5519,
      "a": 0.0667
    },
    {
      "t": 1782770099089,
      "h": 0.548,
      "a": 0.0649
    },
    {
      "t": 1782770130185,
      "h": 0.5397,
      "a": 0.0667
    },
    {
      "t": 1782770160199,
      "h": 0.5403,
      "a": 0.068
    },
    {
      "t": 1782770192138,
      "h": 0.5376,
      "a": 0.0637
    },
    {
      "t": 1782770225222,
      "h": 0.5351,
      "a": 0.0633
    },
    {
      "t": 1782770255233,
      "h": 0.5311,
      "a": 0.0637
    },
    {
      "t": 1782770286705,
      "h": 0.5379,
      "a": 0.0633
    },
    {
      "t": 1782770317154,
      "h": 0.5333,
      "a": 0.0617
    },
    {
      "t": 1782770347935,
      "h": 0.526,
      "a": 0.0621
    },
    {
      "t": 1782770377988,
      "h": 0.5203,
      "a": 0.0602
    },
    {
      "t": 1782770408008,
      "h": 0.5192,
      "a": 0.0606
    },
    {
      "t": 1782770438993,
      "h": 0.5033,
      "a": 0.0625
    },
    {
      "t": 1782770469132,
      "h": 0.488,
      "a": 0.0658
    },
    {
      "t": 1782770500190,
      "h": 0.4861,
      "a": 0.0641
    },
    {
      "t": 1782770533124,
      "h": 0.4719,
      "a": 0.0667
    },
    {
      "t": 1782770563139,
      "h": 0.4684,
      "a": 0.0637
    },
    {
      "t": 1782770595560,
      "h": 0.4739,
      "a": 0.0602
    },
    {
      "t": 1782770632359,
      "h": 0.4664,
      "a": 0.0606
    },
    {
      "t": 1782770664366,
      "h": 0.4548,
      "a": 0.0614
    },
    {
      "t": 1782770694375,
      "h": 0.457,
      "a": 0.0614
    },
    {
      "t": 1782770729160,
      "h": 0.4632,
      "a": 0.0617
    },
    {
      "t": 1782770760397,
      "h": 0.4564,
      "a": 0.0633
    },
    {
      "t": 1782770790405,
      "h": 0.4579,
      "a": 0.0606
    },
    {
      "t": 1782770820413,
      "h": 0.4505,
      "a": 0.0641
    },
    {
      "t": 1782770850421,
      "h": 0.4466,
      "a": 0.0649
    },
    {
      "t": 1782770881900,
      "h": 0.4482,
      "a": 0.0625
    },
    {
      "t": 1782770915444,
      "h": 0.4399,
      "a": 0.0649
    },
    {
      "t": 1782770946300,
      "h": 0.4329,
      "a": 0.0629
    },
    {
      "t": 1782770976461,
      "h": 0.4292,
      "a": 0.0621
    },
    {
      "t": 1782771006470,
      "h": 0.4259,
      "a": 0.0606
    },
    {
      "t": 1782771038453,
      "h": 0.4211,
      "a": 0.0602
    },
    {
      "t": 1782771070487,
      "h": 0.4221,
      "a": 0.0565
    },
    {
      "t": 1782771100499,
      "h": 0.4202,
      "a": 0.0585
    },
    {
      "t": 1782771130512,
      "h": 0.416,
      "a": 0.0568
    },
    {
      "t": 1782771161511,
      "h": 0.4105,
      "a": 0.0565
    },
    {
      "t": 1782771191600,
      "h": 0.4019,
      "a": 0.055
    },
    {
      "t": 1782771222535,
      "h": 0.3973,
      "a": 0.055
    },
    {
      "t": 1782771253980,
      "h": 0.3915,
      "a": 0.0544
    },
    {
      "t": 1782771284493,
      "h": 0.3858,
      "a": 0.0541
    },
    {
      "t": 1782771315203,
      "h": 0.3807,
      "a": 0.0529
    },
    {
      "t": 1782771345205,
      "h": 0.3727,
      "a": 0.0524
    },
    {
      "t": 1782771375228,
      "h": 0.3636,
      "a": 0.0503
    },
    {
      "t": 1782771405581,
      "h": 0.3568,
      "a": 0.0497
    },
    {
      "t": 1782771435588,
      "h": 0.3445,
      "a": 0.0518
    },
    {
      "t": 1782771465593,
      "h": 0.336,
      "a": 0.0505
    },
    {
      "t": 1782771495604,
      "h": 0.329,
      "a": 0.0483
    },
    {
      "t": 1782771525613,
      "h": 0.3132,
      "a": 0.0476
    },
    {
      "t": 1782771556157,
      "h": 0.2988,
      "a": 0.0483
    },
    {
      "t": 1782771586637,
      "h": 0.2942,
      "a": 0.0444
    },
    {
      "t": 1782771616649,
      "h": 0.2839,
      "a": 0.0426
    },
    {
      "t": 1782771646658,
      "h": 0.2677,
      "a": 0.04
    },
    {
      "t": 1782771678666,
      "h": 0.2542,
      "a": 0.0372
    },
    {
      "t": 1782771710262,
      "h": 0.2396,
      "a": 0.037
    },
    {
      "t": 1782771740480,
      "h": 0.2241,
      "a": 0.0385
    },
    {
      "t": 1782771770701,
      "h": 0.2104,
      "a": 0.0412
    },
    {
      "t": 1782771803317,
      "h": 0.2045,
      "a": 0.0431
    },
    {
      "t": 1782771851348,
      "h": 0.1825,
      "a": 0.0302
    },
    {
      "t": 1782771882722,
      "h": 0.1581,
      "a": 0.0283
    },
    {
      "t": 1782771914179,
      "h": 0.1524,
      "a": 0.0253
    },
    {
      "t": 1782771945251,
      "h": 0.1202,
      "a": 0.0295
    },
    {
      "t": 1782771975254,
      "h": 0.1151,
      "a": 0.0253
    },
    {
      "t": 1782772005756,
      "h": 0.0787,
      "a": 0.0213
    }
  ],
  "computedAt": "2026-07-15T07:27:25.796Z"
}