{
  "matchId": "18179759",
  "homeTeam": "Mexico",
  "awayTeam": "Ecuador",
  "homeScore": 2,
  "awayScore": 0,
  "phase": "F",
  "winner": "home",
  "keyEvents": [
    {
      "type": "goal",
      "team": "home",
      "minute": 22,
      "timestamp": 1782872525148
    },
    {
      "type": "goal",
      "team": "home",
      "minute": 31,
      "timestamp": 1782873079894
    },
    {
      "type": "yellow_card",
      "team": "away",
      "minute": 47,
      "timestamp": 1782874010047
    },
    {
      "type": "yellow_card",
      "team": "away",
      "minute": 93,
      "timestamp": 1782878099132
    },
    {
      "type": "var_end",
      "team": null,
      "minute": 95,
      "timestamp": 1782878216589
    },
    {
      "type": "red_card",
      "team": "away",
      "minute": 95,
      "timestamp": 1782878219832
    },
    {
      "type": "yellow_card",
      "team": "away",
      "minute": 99,
      "timestamp": 1782878441248
    }
  ],
  "fires": [],
  "probSeries": [
    {
      "t": 1782867644637,
      "h": 0.4177,
      "a": 0.232
    },
    {
      "t": 1782867704838,
      "h": 0.417,
      "a": 0.2327
    },
    {
      "t": 1782867744972,
      "h": 0.4172,
      "a": 0.2327
    },
    {
      "t": 1782867909527,
      "h": 0.4175,
      "a": 0.2326
    },
    {
      "t": 1782867944642,
      "h": 0.4179,
      "a": 0.2325
    },
    {
      "t": 1782868039060,
      "h": 0.4184,
      "a": 0.2332
    },
    {
      "t": 1782868155599,
      "h": 0.4182,
      "a": 0.2336
    },
    {
      "t": 1782868314885,
      "h": 0.4177,
      "a": 0.2339
    },
    {
      "t": 1782868435607,
      "h": 0.416,
      "a": 0.2341
    },
    {
      "t": 1782868480556,
      "h": 0.4167,
      "a": 0.2347
    },
    {
      "t": 1782868538788,
      "h": 0.4146,
      "a": 0.2368
    },
    {
      "t": 1782868985087,
      "h": 0.4155,
      "a": 0.236
    },
    {
      "t": 1782869015839,
      "h": 0.4172,
      "a": 0.2348
    },
    {
      "t": 1782869387020,
      "h": 0.4175,
      "a": 0.2334
    },
    {
      "t": 1782869579078,
      "h": 0.4177,
      "a": 0.2331
    },
    {
      "t": 1782869609175,
      "h": 0.4168,
      "a": 0.2338
    },
    {
      "t": 1782869639270,
      "h": 0.4149,
      "a": 0.2346
    },
    {
      "t": 1782869685660,
      "h": 0.416,
      "a": 0.2351
    },
    {
      "t": 1782869725665,
      "h": 0.4158,
      "a": 0.2351
    },
    {
      "t": 1782869880066,
      "h": 0.4139,
      "a": 0.2358
    },
    {
      "t": 1782869947953,
      "h": 0.4139,
      "a": 0.2357
    },
    {
      "t": 1782870024558,
      "h": 0.4141,
      "a": 0.2358
    },
    {
      "t": 1782870175052,
      "h": 0.4149,
      "a": 0.2352
    },
    {
      "t": 1782870277484,
      "h": 0.4137,
      "a": 0.2365
    },
    {
      "t": 1782870362959,
      "h": 0.4132,
      "a": 0.2368
    },
    {
      "t": 1782870414874,
      "h": 0.4137,
      "a": 0.2366
    },
    {
      "t": 1782870444976,
      "h": 0.4144,
      "a": 0.236
    },
    {
      "t": 1782870500985,
      "h": 0.4146,
      "a": 0.2357
    },
    {
      "t": 1782870570694,
      "h": 0.4146,
      "a": 0.2358
    },
    {
      "t": 1782870604506,
      "h": 0.4153,
      "a": 0.2364
    },
    {
      "t": 1782870639623,
      "h": 0.4131,
      "a": 0.2379
    },
    {
      "t": 1782870739955,
      "h": 0.4131,
      "a": 0.2379
    },
    {
      "t": 1782870797998,
      "h": 0.4127,
      "a": 0.238
    },
    {
      "t": 1782870834262,
      "h": 0.4122,
      "a": 0.2383
    },
    {
      "t": 1782870875706,
      "h": 0.4122,
      "a": 0.2382
    },
    {
      "t": 1782870948031,
      "h": 0.412,
      "a": 0.2383
    },
    {
      "t": 1782871010714,
      "h": 0.4125,
      "a": 0.238
    },
    {
      "t": 1782871040714,
      "h": 0.4124,
      "a": 0.238
    },
    {
      "t": 1782871085080,
      "h": 0.4122,
      "a": 0.2384
    },
    {
      "t": 1782871124210,
      "h": 0.4117,
      "a": 0.2389
    },
    {
      "t": 1782871167038,
      "h": 0.4122,
      "a": 0.2384
    },
    {
      "t": 1782871199206,
      "h": 0.4136,
      "a": 0.24
    },
    {
      "t": 1782871239584,
      "h": 0.4144,
      "a": 0.2384
    },
    {
      "t": 1782871272398,
      "h": 0.4146,
      "a": 0.239
    },
    {
      "t": 1782871310251,
      "h": 0.4112,
      "a": 0.239
    },
    {
      "t": 1782871340339,
      "h": 0.4136,
      "a": 0.2378
    },
    {
      "t": 1782871371005,
      "h": 0.4144,
      "a": 0.2357
    },
    {
      "t": 1782871402101,
      "h": 0.4125,
      "a": 0.2371
    },
    {
      "t": 1782871434104,
      "h": 0.4102,
      "a": 0.2359
    },
    {
      "t": 1782871464105,
      "h": 0.4167,
      "a": 0.2321
    },
    {
      "t": 1782871502111,
      "h": 0.4216,
      "a": 0.2281
    },
    {
      "t": 1782871533062,
      "h": 0.4259,
      "a": 0.225
    },
    {
      "t": 1782871570098,
      "h": 0.431,
      "a": 0.2191
    },
    {
      "t": 1782871600142,
      "h": 0.435,
      "a": 0.2177
    },
    {
      "t": 1782871630620,
      "h": 0.4433,
      "a": 0.2122
    },
    {
      "t": 1782871664696,
      "h": 0.4482,
      "a": 0.2075
    },
    {
      "t": 1782871697222,
      "h": 0.4606,
      "a": 0.1981
    },
    {
      "t": 1782871727246,
      "h": 0.4647,
      "a": 0.1962
    },
    {
      "t": 1782871759685,
      "h": 0.4619,
      "a": 0.198
    },
    {
      "t": 1782871803157,
      "h": 0.4645,
      "a": 0.1957
    },
    {
      "t": 1782871838170,
      "h": 0.4602,
      "a": 0.1992
    },
    {
      "t": 1782871869332,
      "h": 0.4579,
      "a": 0.2022
    },
    {
      "t": 1782871903191,
      "h": 0.4539,
      "a": 0.2029
    },
    {
      "t": 1782871934158,
      "h": 0.4556,
      "a": 0.2034
    },
    {
      "t": 1782871964574,
      "h": 0.455,
      "a": 0.2024
    },
    {
      "t": 1782871996168,
      "h": 0.4511,
      "a": 0.2076
    },
    {
      "t": 1782872027227,
      "h": 0.4556,
      "a": 0.2017
    },
    {
      "t": 1782872058174,
      "h": 0.4509,
      "a": 0.204
    },
    {
      "t": 1782872089247,
      "h": 0.4531,
      "a": 0.2023
    },
    {
      "t": 1782872123256,
      "h": 0.4566,
      "a": 0.1998
    },
    {
      "t": 1782872154706,
      "h": 0.4589,
      "a": 0.1996
    },
    {
      "t": 1782872184715,
      "h": 0.457,
      "a": 0.1996
    },
    {
      "t": 1782872217022,
      "h": 0.4562,
      "a": 0.2004
    },
    {
      "t": 1782872251291,
      "h": 0.4581,
      "a": 0.1952
    },
    {
      "t": 1782872281324,
      "h": 0.4537,
      "a": 0.199
    },
    {
      "t": 1782872312197,
      "h": 0.4537,
      "a": 0.2006
    },
    {
      "t": 1782872345323,
      "h": 0.4492,
      "a": 0.2018
    },
    {
      "t": 1782872375333,
      "h": 0.449,
      "a": 0.2021
    },
    {
      "t": 1782872411341,
      "h": 0.4423,
      "a": 0.2052
    },
    {
      "t": 1782872444655,
      "h": 0.445,
      "a": 0.2046
    },
    {
      "t": 1782872469654,
      "h": 0.4439,
      "a": 0.2067
    },
    {
      "t": 1782872474695,
      "h": 0.4429,
      "a": 0.2066
    },
    {
      "t": 1782872484682,
      "h": 0.4423,
      "a": 0.2069
    },
    {
      "t": 1782872504286,
      "h": 0.4423,
      "a": 0.2067
    },
    {
      "t": 1782872511172,
      "h": 0.4401,
      "a": 0.2076
    },
    {
      "t": 1782872519376,
      "h": 0.4399,
      "a": 0.2066
    },
    {
      "t": 1782872584725,
      "h": 0.7353,
      "a": 0.0714
    },
    {
      "t": 1782872594215,
      "h": 0.7321,
      "a": 0.0735
    },
    {
      "t": 1782872599618,
      "h": 0.7315,
      "a": 0.0735
    },
    {
      "t": 1782872608482,
      "h": 0.7194,
      "a": 0.0807
    },
    {
      "t": 1782872618736,
      "h": 0.7257,
      "a": 0.0763
    },
    {
      "t": 1782872624359,
      "h": 0.7215,
      "a": 0.0758
    },
    {
      "t": 1782872629364,
      "h": 0.7174,
      "a": 0.0775
    },
    {
      "t": 1782872634666,
      "h": 0.7163,
      "a": 0.0763
    },
    {
      "t": 1782872640214,
      "h": 0.7179,
      "a": 0.0775
    },
    {
      "t": 1782872648369,
      "h": 0.7199,
      "a": 0.0769
    },
    {
      "t": 1782872654680,
      "h": 0.7189,
      "a": 0.0752
    },
    {
      "t": 1782872659699,
      "h": 0.7184,
      "a": 0.0758
    },
    {
      "t": 1782872665758,
      "h": 0.7143,
      "a": 0.0775
    },
    {
      "t": 1782872675429,
      "h": 0.7133,
      "a": 0.0775
    },
    {
      "t": 1782872681447,
      "h": 0.7122,
      "a": 0.0775
    },
    {
      "t": 1782872694702,
      "h": 0.7128,
      "a": 0.0775
    },
    {
      "t": 1782872705405,
      "h": 0.7128,
      "a": 0.0758
    },
    {
      "t": 1782872720105,
      "h": 0.7133,
      "a": 0.0775
    },
    {
      "t": 1782872733455,
      "h": 0.7158,
      "a": 0.0769
    },
    {
      "t": 1782872739455,
      "h": 0.7184,
      "a": 0.0752
    },
    {
      "t": 1782872745721,
      "h": 0.7199,
      "a": 0.0741
    },
    {
      "t": 1782872751456,
      "h": 0.7199,
      "a": 0.073
    },
    {
      "t": 1782872763459,
      "h": 0.7225,
      "a": 0.0735
    },
    {
      "t": 1782872771723,
      "h": 0.722,
      "a": 0.0741
    },
    {
      "t": 1782872779459,
      "h": 0.721,
      "a": 0.073
    },
    {
      "t": 1782872790227,
      "h": 0.722,
      "a": 0.073
    },
    {
      "t": 1782872795465,
      "h": 0.722,
      "a": 0.0741
    },
    {
      "t": 1782872802229,
      "h": 0.7246,
      "a": 0.0752
    },
    {
      "t": 1782872809658,
      "h": 0.7231,
      "a": 0.0775
    },
    {
      "t": 1782872818229,
      "h": 0.7225,
      "a": 0.0775
    },
    {
      "t": 1782872823471,
      "h": 0.722,
      "a": 0.0763
    },
    {
      "t": 1782872854627,
      "h": 0.7194,
      "a": 0.0746
    },
    {
      "t": 1782872888234,
      "h": 0.7241,
      "a": 0.073
    },
    {
      "t": 1782872920555,
      "h": 0.7184,
      "a": 0.0725
    },
    {
      "t": 1782872954650,
      "h": 0.7189,
      "a": 0.0676
    },
    {
      "t": 1782872986241,
      "h": 0.7169,
      "a": 0.0741
    },
    {
      "t": 1782873019085,
      "h": 0.7143,
      "a": 0.0741
    },
    {
      "t": 1782873025083,
      "h": 0.7148,
      "a": 0.0741
    },
    {
      "t": 1782873039098,
      "h": 0.7148,
      "a": 0.0741
    },
    {
      "t": 1782873044843,
      "h": 0.7158,
      "a": 0.0741
    },
    {
      "t": 1782873056419,
      "h": 0.7184,
      "a": 0.0714
    },
    {
      "t": 1782873067536,
      "h": 0.7148,
      "a": 0.0725
    },
    {
      "t": 1782873073542,
      "h": 0.7199,
      "a": 0.0667
    },
    {
      "t": 1782873136550,
      "h": 0.9166,
      "a": 0.0167
    },
    {
      "t": 1782873142254,
      "h": 0.9174,
      "a": 0.0159
    },
    {
      "t": 1782873158256,
      "h": 0.9174,
      "a": 0.0161
    },
    {
      "t": 1782873166444,
      "h": 0.9225,
      "a": 0.0147
    },
    {
      "t": 1782873174224,
      "h": 0.9234,
      "a": 0.0149
    },
    {
      "t": 1782873179847,
      "h": 0.9234,
      "a": 0.0145
    },
    {
      "t": 1782873186198,
      "h": 0.9242,
      "a": 0.0143
    },
    {
      "t": 1782873194270,
      "h": 0.9234,
      "a": 0.0145
    },
    {
      "t": 1782873205209,
      "h": 0.9225,
      "a": 0.0145
    },
    {
      "t": 1782873216542,
      "h": 0.9225,
      "a": 0.0145
    },
    {
      "t": 1782873221817,
      "h": 0.9225,
      "a": 0.0145
    },
    {
      "t": 1782873239542,
      "h": 0.9225,
      "a": 0.0145
    },
    {
      "t": 1782873247818,
      "h": 0.9217,
      "a": 0.0147
    },
    {
      "t": 1782873255029,
      "h": 0.9217,
      "a": 0.0143
    },
    {
      "t": 1782873273060,
      "h": 0.9208,
      "a": 0.0137
    },
    {
      "t": 1782873280253,
      "h": 0.9208,
      "a": 0.0139
    },
    {
      "t": 1782873289678,
      "h": 0.9217,
      "a": 0.0147
    },
    {
      "t": 1782873298069,
      "h": 0.9208,
      "a": 0.0145
    },
    {
      "t": 1782873310270,
      "h": 0.92,
      "a": 0.0147
    },
    {
      "t": 1782873316460,
      "h": 0.9217,
      "a": 0.0151
    },
    {
      "t": 1782873324287,
      "h": 0.92,
      "a": 0.0154
    },
    {
      "t": 1782873329557,
      "h": 0.92,
      "a": 0.0156
    },
    {
      "t": 1782873338270,
      "h": 0.9208,
      "a": 0.0156
    },
    {
      "t": 1782873346456,
      "h": 0.9208,
      "a": 0.0159
    },
    {
      "t": 1782873354271,
      "h": 0.9183,
      "a": 0.0159
    },
    {
      "t": 1782873373842,
      "h": 0.9191,
      "a": 0.0161
    },
    {
      "t": 1782873406508,
      "h": 0.9132,
      "a": 0.0164
    },
    {
      "t": 1782873438386,
      "h": 0.9132,
      "a": 0.0164
    },
    {
      "t": 1782873469404,
      "h": 0.9158,
      "a": 0.0175
    },
    {
      "t": 1782873499708,
      "h": 0.9174,
      "a": 0.017
    },
    {
      "t": 1782873531554,
      "h": 0.9124,
      "a": 0.0185
    },
    {
      "t": 1782873564727,
      "h": 0.9174,
      "a": 0.0175
    },
    {
      "t": 1782873594761,
      "h": 0.9217,
      "a": 0.0164
    },
    {
      "t": 1782873632530,
      "h": 0.9174,
      "a": 0.017
    },
    {
      "t": 1782873668551,
      "h": 0.9116,
      "a": 0.0196
    },
    {
      "t": 1782873702209,
      "h": 0.9124,
      "a": 0.0192
    },
    {
      "t": 1782873732316,
      "h": 0.9108,
      "a": 0.0192
    },
    {
      "t": 1782873763846,
      "h": 0.9083,
      "a": 0.0204
    },
    {
      "t": 1782873796135,
      "h": 0.905,
      "a": 0.0203
    },
    {
      "t": 1782873828323,
      "h": 0.9042,
      "a": 0.0201
    },
    {
      "t": 1782873859729,
      "h": 0.9074,
      "a": 0.02
    },
    {
      "t": 1782873890336,
      "h": 0.905,
      "a": 0.0207
    },
    {
      "t": 1782873928337,
      "h": 0.9083,
      "a": 0.0182
    },
    {
      "t": 1782873967066,
      "h": 0.9124,
      "a": 0.0179
    },
    {
      "t": 1782874004417,
      "h": 0.9132,
      "a": 0.0179
    },
    {
      "t": 1782874038323,
      "h": 0.9116,
      "a": 0.0172
    },
    {
      "t": 1782874074719,
      "h": 0.9141,
      "a": 0.0175
    },
    {
      "t": 1782874106357,
      "h": 0.9124,
      "a": 0.0164
    },
    {
      "t": 1782874136392,
      "h": 0.9116,
      "a": 0.0164
    },
    {
      "t": 1782874171236,
      "h": 0.9183,
      "a": 0.0167
    },
    {
      "t": 1782874201353,
      "h": 0.9191,
      "a": 0.0161
    },
    {
      "t": 1782874240060,
      "h": 0.9217,
      "a": 0.0151
    },
    {
      "t": 1782874275040,
      "h": 0.9217,
      "a": 0.0159
    },
    {
      "t": 1782874316369,
      "h": 0.9234,
      "a": 0.0159
    },
    {
      "t": 1782874349872,
      "h": 0.9158,
      "a": 0.0154
    },
    {
      "t": 1782874385037,
      "h": 0.9217,
      "a": 0.0154
    },
    {
      "t": 1782874421024,
      "h": 0.9191,
      "a": 0.0156
    },
    {
      "t": 1782874455393,
      "h": 0.9158,
      "a": 0.0151
    },
    {
      "t": 1782874488089,
      "h": 0.9242,
      "a": 0.0156
    },
    {
      "t": 1782874520393,
      "h": 0.9251,
      "a": 0.0161
    },
    {
      "t": 1782874560065,
      "h": 0.9285,
      "a": 0.0147
    },
    {
      "t": 1782874599108,
      "h": 0.9311,
      "a": 0.0147
    },
    {
      "t": 1782874634404,
      "h": 0.9191,
      "a": 0.0151
    },
    {
      "t": 1782874667208,
      "h": 0.9191,
      "a": 0.0151
    },
    {
      "t": 1782874703264,
      "h": 0.9174,
      "a": 0.0147
    },
    {
      "t": 1782874736414,
      "h": 0.9149,
      "a": 0.0151
    },
    {
      "t": 1782874799867,
      "h": 0.9149,
      "a": 0.0132
    },
    {
      "t": 1782874876423,
      "h": 0.9141,
      "a": 0.0151
    },
    {
      "t": 1782874908884,
      "h": 0.9191,
      "a": 0.0164
    },
    {
      "t": 1782874952423,
      "h": 0.9234,
      "a": 0.0172
    },
    {
      "t": 1782874994427,
      "h": 0.9166,
      "a": 0.0154
    },
    {
      "t": 1782875032511,
      "h": 0.9174,
      "a": 0.0154
    },
    {
      "t": 1782875085256,
      "h": 0.9208,
      "a": 0.0156
    },
    {
      "t": 1782875126562,
      "h": 0.9259,
      "a": 0.0159
    },
    {
      "t": 1782875165591,
      "h": 0.9285,
      "a": 0.0151
    },
    {
      "t": 1782875196446,
      "h": 0.9183,
      "a": 0.0161
    },
    {
      "t": 1782875228449,
      "h": 0.9217,
      "a": 0.0143
    },
    {
      "t": 1782875268261,
      "h": 0.9191,
      "a": 0.0151
    },
    {
      "t": 1782875301206,
      "h": 0.9242,
      "a": 0.0143
    },
    {
      "t": 1782875339226,
      "h": 0.9276,
      "a": 0.0149
    },
    {
      "t": 1782875370658,
      "h": 0.9251,
      "a": 0.0151
    },
    {
      "t": 1782875410290,
      "h": 0.9285,
      "a": 0.0147
    },
    {
      "t": 1782875446309,
      "h": 0.9285,
      "a": 0.0147
    },
    {
      "t": 1782875480315,
      "h": 0.9302,
      "a": 0.0137
    },
    {
      "t": 1782875511360,
      "h": 0.932,
      "a": 0.0125
    },
    {
      "t": 1782875542477,
      "h": 0.9328,
      "a": 0.0121
    },
    {
      "t": 1782875574328,
      "h": 0.9328,
      "a": 0.0124
    },
    {
      "t": 1782875604481,
      "h": 0.9355,
      "a": 0.0124
    },
    {
      "t": 1782875635105,
      "h": 0.9372,
      "a": 0.0112
    },
    {
      "t": 1782875665381,
      "h": 0.9381,
      "a": 0.0112
    },
    {
      "t": 1782875698003,
      "h": 0.939,
      "a": 0.011
    },
    {
      "t": 1782875728061,
      "h": 0.9416,
      "a": 0.0109
    },
    {
      "t": 1782875758482,
      "h": 0.9416,
      "a": 0.0106
    },
    {
      "t": 1782875789544,
      "h": 0.9443,
      "a": 0.0106
    },
    {
      "t": 1782875828573,
      "h": 0.9416,
      "a": 0.0105
    },
    {
      "t": 1782875862505,
      "h": 0.9434,
      "a": 0.01
    },
    {
      "t": 1782875892506,
      "h": 0.9434,
      "a": 0.01
    },
    {
      "t": 1782875926187,
      "h": 0.9443,
      "a": 0.0091
    },
    {
      "t": 1782875960168,
      "h": 0.9434,
      "a": 0.01
    },
    {
      "t": 1782875994437,
      "h": 0.9443,
      "a": 0.01
    },
    {
      "t": 1782876025399,
      "h": 0.9452,
      "a": 0.01
    },
    {
      "t": 1782876056453,
      "h": 0.9461,
      "a": 0.0091
    },
    {
      "t": 1782876089766,
      "h": 0.9479,
      "a": 0.01
    },
    {
      "t": 1782876128547,
      "h": 0.9461,
      "a": 0.0101
    },
    {
      "t": 1782876164903,
      "h": 0.9506,
      "a": 0.0091
    },
    {
      "t": 1782876198568,
      "h": 0.947,
      "a": 0.0091
    },
    {
      "t": 1782876253395,
      "h": 0.9443,
      "a": 0.0091
    },
    {
      "t": 1782876284734,
      "h": 0.9443,
      "a": 0.0091
    },
    {
      "t": 1782876322369,
      "h": 0.9425,
      "a": 0.0091
    },
    {
      "t": 1782876355390,
      "h": 0.9407,
      "a": 0.0091
    },
    {
      "t": 1782876392305,
      "h": 0.9452,
      "a": 0.0091
    },
    {
      "t": 1782876425386,
      "h": 0.9452,
      "a": 0.0083
    },
    {
      "t": 1782876466560,
      "h": 0.9479,
      "a": 0.0077
    },
    {
      "t": 1782876499475,
      "h": 0.9479,
      "a": 0.0077
    },
    {
      "t": 1782876533489,
      "h": 0.9542,
      "a": 0.0071
    },
    {
      "t": 1782876564857,
      "h": 0.9551,
      "a": 0.0077
    },
    {
      "t": 1782876598600,
      "h": 0.9515,
      "a": 0.0077
    },
    {
      "t": 1782876642574,
      "h": 0.9551,
      "a": 0.0067
    },
    {
      "t": 1782876754583,
      "h": 0.9681,
      "a": 0.0048
    },
    {
      "t": 1782876790020,
      "h": 0.9643,
      "a": 0.0056
    },
    {
      "t": 1782876822131,
      "h": 0.9625,
      "a": 0.0059
    },
    {
      "t": 1782876912601,
      "h": 0.9653,
      "a": 0.0053
    },
    {
      "t": 1782876949698,
      "h": 0.9653,
      "a": 0.005
    },
    {
      "t": 1782877004704,
      "h": 0.9681,
      "a": 0.0048
    },
    {
      "t": 1782877044614,
      "h": 0.9588,
      "a": 0.0063
    },
    {
      "t": 1782877139189,
      "h": 0.9606,
      "a": 0.0044
    },
    {
      "t": 1782877193701,
      "h": 0.9615,
      "a": 0.0044
    },
    {
      "t": 1782877232624,
      "h": 0.9681,
      "a": 0.0046
    },
    {
      "t": 1782877263212,
      "h": 0.9662,
      "a": 0.0039
    },
    {
      "t": 1782877415972,
      "h": 0.9756,
      "a": 0.0036
    },
    {
      "t": 1782877454945,
      "h": 0.9785,
      "a": 0.0027
    },
    {
      "t": 1782877488226,
      "h": 0.9785,
      "a": 0.0037
    },
    {
      "t": 1782877574782,
      "h": 0.9756,
      "a": 0.0035
    },
    {
      "t": 1782877607364,
      "h": 0.9823,
      "a": 0.0035
    },
    {
      "t": 1782877641172,
      "h": 0.9823,
      "a": 0.0035
    }
  ],
  "computedAt": "2026-07-15T07:27:29.537Z"
}